pyjsonq/__init__.py
pyjsonq/errors.py
pyjsonq/helper.py
pyjsonq/parser.py
pyjsonq/query.py
pyjsonquery-2.1.2.dist-info/LICENSE
pyjsonquery-2.1.2.dist-info/METADATA
pyjsonquery-2.1.2.dist-info/WHEEL
pyjsonquery-2.1.2.dist-info/top_level.txt
pyjsonquery-2.1.2.dist-info/RECORD
