Metadata-Version: 2.1
Name: pyjsonquery
Version: 2.1.2
Summary: A simple to use query api for json data
Home-page: https://github.com/florian-obernberger/pyjsonq
Author: Florian Obernberger
Author-email: florian.obernberger@gmail.com
License: MIT License
Project-URL: Bug Tracker, https://github.com/florian-obernberger/pyjsonq/issues
Keywords: json,json query,json api,query api,query
Classifier: Programming Language :: Python :: 3
Classifier: License :: OSI Approved :: MIT License
Classifier: Operating System :: OS Independent
Requires-Python: >=3.6
License-File: LICENSE
Requires-Dist: toml
